kladia/__init__.py
kladia/graph.py
kladia/utils.py
kladia-0.0.1.dist-info/LICENSE
kladia-0.0.1.dist-info/METADATA
kladia-0.0.1.dist-info/WHEEL
kladia-0.0.1.dist-info/top_level.txt
kladia-0.0.1.dist-info/RECORD
