Metadata-Version: 2.1
Name: kladia
Version: 0.0.1
Summary: A simple and minimal graph library based on Python dictionaries.
Author-email: Jocer Franquiz <author@example.com>
Project-URL: Homepage, https://github.com/jocerfranquiz/kladia
Project-URL: Bug Tracker, https://github.com/jocerfranquiz/kladia/issues
Classifier: Programming Language :: Python :: 3
Classifier: License :: OSI Approved :: MIT License
Classifier: Operating System :: OS Independent
Requires-Python: >=3.10
License-File: LICENSE
